find_remove_blank_pdf/__init__.py
find_remove_blank_pdf/sdk.py
find_remove_blank_pdf-0.0.1.dist-info/METADATA
find_remove_blank_pdf-0.0.1.dist-info/WHEEL
find_remove_blank_pdf-0.0.1.dist-info/top_level.txt
find_remove_blank_pdf-0.0.1.dist-info/RECORD
